{
    "class" : "HiddenMarkovModel",
    "name" : "C",
    "start" : {
        "class" : "State",
        "distribution" : null,
        "name" : "C-start",
        "weight" : 1.0
    },
    "end" : {
        "class" : "State",
        "distribution" : null,
        "name" : "C-end",
        "weight" : 1.0
    },
    "states" : [
        {
            "class" : "State",
            "distribution" : {
                "class" : "Distribution",
                "dtype" : "int",
                "name" : "DiscreteDistribution",
                "parameters" : [
                    {
                        "0" : 0.05456769158041512,
                        "1" : 0.036754433080809716,
                        "2" : 0.0018756495821734861,
                        "3" : 0.0010255844853266226,
                        "4" : 0.0008046969375518152,
                        "5" : 0.002894553058876385,
                        "6" : 0.00021348137944097315,
                        "7" : 0.0004052000961881664,
                        "8" : 0.00010655204802330618,
                        "9" : 0.0003466042294061263,
                        "10" : 3.5407858961029904e-10,
                        "11" : 7.2696992711850674e-09,
                        "12" : 8.95714719282393e-07,
                        "13" : 3.3018843526508323e-13,
                        "14" : 3.100927382407633e-07,
                        "15" : 2.4447764818936954e-19,
                        "16" : 0.031732470032769404,
                        "17" : 0.033601817542437185,
                        "18" : 0.00873125806436832,
                        "19" : 0.014795252635710935,
                        "20" : 0.0002912454026750596,
                        "21" : 3.3762688395284515e-05,
                        "22" : 1.1160226414387777e-06,
                        "23" : 0.0002362490405601316,
                        "24" : 0.0,
                        "25" : 0.0,
                        "26" : 0.0,
                        "27" : 5.246521301122558e-16,
                        "28" : 0.0001692387503788361,
                        "29" : 0.0,
                        "30" : 0.0,
                        "31" : 0.0,
                        "32" : 4.943806063898565e-05,
                        "33" : 5.640350308556936e-12,
                        "34" : 1.3287354425926246e-14,
                        "35" : 0.0,
                        "36" : 8.046887286886178e-10,
                        "37" : 0.0,
                        "38" : 0.0,
                        "39" : 0.0,
                        "40" : 7.652066203556399e-13,
                        "41" : 5.376891179847316e-05,
                        "42" : 1.0182748163566013e-15,
                        "43" : 0.00010753774362301113,
                        "44" : 0.00021922711069025203,
                        "45" : 2.158045117846796e-15,
                        "46" : 0.0005695799055238703,
                        "47" : 8.752363690362895e-07,
                        "48" : 1.2331674532628304e-11,
                        "49" : 7.391125885459826e-06,
                        "50" : 0.0,
                        "51" : 0.0,
                        "52" : 7.415609769859054e-05,
                        "53" : 8.241700102893975e-06,
                        "54" : 0.0,
                        "55" : 0.0,
                        "56" : 2.231324535269741e-05,
                        "57" : 7.419263869825825e-17,
                        "58" : 0.0,
                        "59" : 0.0,
                        "60" : 0.0,
                        "61" : 0.0,
                        "62" : 3.0876406587555446e-19,
                        "63" : 0.00032995235691280877,
                        "64" : 0.015427251968269417,
                        "65" : 0.010390594326600316,
                        "66" : 0.007070866048656942,
                        "67" : 3.1921764354880863e-05,
                        "68" : 0.0006343409013965042,
                        "69" : 0.00027955678175911115,
                        "70" : 0.005462423794308131,
                        "71" : 0.002128786753183109,
                        "72" : 0.0001301136833456484,
                        "73" : 3.516544581677066e-10,
                        "74" : 0.0008127616994638912,
                        "75" : 7.826811797325248e-05,
                        "76" : 0.0029169018645067647,
                        "77" : 0.0009115942628711839,
                        "78" : 0.0008015223263598334,
                        "79" : 2.4639254738395392e-05,
                        "80" : 0.006599933558942163,
                        "81" : 0.00047413834243877024,
                        "82" : 0.005336656434765491,
                        "83" : 1.6328459677246692e-09,
                        "84" : 0.008924432657055066,
                        "85" : 0.002351398575492301,
                        "86" : 0.0003735849571247503,
                        "87" : 1.4811795290025652e-10,
                        "88" : 0.00035641576437584014,
                        "89" : 4.19003716928185e-05,
                        "90" : 0.0009725572932529414,
                        "91" : 0.03677211462330154,
                        "92" : 0.09929797813987859,
                        "93" : 0.008917672616708734,
                        "94" : 0.024584674374455683,
                        "95" : 0.0004722013239390772,
                        "96" : 0.07447792664161298,
                        "97" : 0.07746169492644137,
                        "98" : 0.03707800572169294,
                        "99" : 0.10001521908976241,
                        "100" : 0.0034512794758805405,
                        "101" : 0.010500473456814615,
                        "102" : 0.013831478970229764,
                        "103" : 1.5612425670747855e-06,
                        "104" : 0.0225706041574586,
                        "105" : 0.03863838499452916,
                        "106" : 0.0045011049513774964,
                        "107" : 0.029596293459653554,
                        "108" : 0.06249153068363483,
                        "109" : 0.01041598681111939,
                        "110" : 0.001044840199464783,
                        "111" : 0.00016847656839828672,
                        "112" : 0.07610033235320811,
                        "113" : 0.002582283191881506,
                        "114" : 0.00019130889855532228,
                        "115" : 5.691382745420448e-11,
                        "116" : 0.0013044625514195456,
                        "117" : 2.0094535816776496e-17,
                        "118" : 1.7282614064043012e-08,
                        "119" : 8.0466103692616e-17,
                        "120" : 0.0008315968588169723,
                        "121" : 7.917915946501297e-12,
                        "122" : 8.28958856078713e-05,
                        "123" : 3.0181435222930334e-16,
                        "124" : 4.682509822447068e-05,
                        "125" : 7.659342620991385e-06,
                        "126" : 3.545587915269499e-17,
                        "127" : 4.654028058730437e-19
                    }
                ],
                "frozen" : false
            },
            "name" : "state0",
            "weight" : 1.0
        },
        {
            "class" : "State",
            "distribution" : {
                "class" : "Distribution",
                "dtype" : "int",
                "name" : "DiscreteDistribution",
                "parameters" : [
                    {
                        "0" : 0.0012043669150883659,
                        "1" : 1.3005750421121094e-06,
                        "2" : 0.0023763546955370774,
                        "3" : 0.0005505777283488255,
                        "4" : 0.00023582012909654482,
                        "5" : 7.95112190011697e-12,
                        "6" : 1.604574027034885e-08,
                        "7" : 0.003271879879085383,
                        "8" : 8.456840351430846e-17,
                        "9" : 3.3689191595391484e-05,
                        "10" : 2.9048376188944836e-07,
                        "11" : 0.000517481003332597,
                        "12" : 1.2440673501496576e-06,
                        "13" : 1.9664691257142977e-17,
                        "14" : 2.407038829560757e-10,
                        "15" : 2.429144290007571e-20,
                        "16" : 0.00013532454061963525,
                        "17" : 0.02746420351372266,
                        "18" : 0.009072278588778496,
                        "19" : 0.0412883834396095,
                        "20" : 0.08038501736417596,
                        "21" : 0.02222060266689912,
                        "22" : 0.05688506774286252,
                        "23" : 0.002841487810785726,
                        "24" : 0.0,
                        "25" : 0.0,
                        "26" : 0.0,
                        "27" : 2.6998703428442925e-17,
                        "28" : 1.2876227496501081e-08,
                        "29" : 0.0,
                        "30" : 0.0,
                        "31" : 0.0,
                        "32" : 0.00013032704261239274,
                        "33" : 2.952559691008616e-10,
                        "34" : 0.00022088031240346704,
                        "35" : 0.0,
                        "36" : 2.370155307843863e-10,
                        "37" : 0.0,
                        "38" : 0.0,
                        "39" : 0.0,
                        "40" : 7.995636049601315e-21,
                        "41" : 3.914258919704305e-22,
                        "42" : 4.6815029873218305e-11,
                        "43" : 1.1000292019658749e-10,
                        "44" : 0.00014330855328724754,
                        "45" : 5.792116473511538e-05,
                        "46" : 0.0009175895038182093,
                        "47" : 0.0002942567726975294,
                        "48" : 1.2294439116070778e-16,
                        "49" : 3.679513042614976e-15,
                        "50" : 0.0,
                        "51" : 0.0,
                        "52" : 7.441908811158844e-05,
                        "53" : 0.00014805590688905912,
                        "54" : 0.0,
                        "55" : 0.0,
                        "56" : 7.778824113196591e-05,
                        "57" : 7.395825305878494e-05,
                        "58" : 0.0,
                        "59" : 0.0,
                        "60" : 0.0,
                        "61" : 0.0,
                        "62" : 9.725488059397325e-19,
                        "63" : 2.565057166178132e-05,
                        "64" : 0.0006852380664261571,
                        "65" : 0.00042172703302889613,
                        "66" : 0.00040905870044492907,
                        "67" : 0.009834785160603744,
                        "68" : 0.0005175220989700811,
                        "69" : 0.0012445902722384666,
                        "70" : 0.00015425717965014427,
                        "71" : 0.0023455880856673344,
                        "72" : 0.03574993678736942,
                        "73" : 0.010000022568400414,
                        "74" : 0.04185383288938416,
                        "75" : 0.018116124279923936,
                        "76" : 0.00289795005786862,
                        "77" : 0.0003550801903478806,
                        "78" : 0.0020557640801328113,
                        "79" : 8.372793326517107e-05,
                        "80" : 3.0303090041546746e-06,
                        "81" : 0.0015665488695203657,
                        "82" : 3.231876096981318e-07,
                        "83" : 1.1845596815370749e-08,
                        "84" : 0.0011993603473764763,
                        "85" : 0.002056066368841056,
                        "86" : 7.410477613332148e-05,
                        "87" : 0.0020016410989930934,
                        "88" : 0.013638202634526135,
                        "89" : 0.00010856660303930963,
                        "90" : 9.129742083599293e-09,
                        "91" : 0.004127283290471314,
                        "92" : 0.0006235578125006036,
                        "93" : 0.0013676555151959893,
                        "94" : 0.021355886822867834,
                        "95" : 0.14748297868142615,
                        "96" : 0.0003411790322238154,
                        "97" : 3.5547806740599e-08,
                        "98" : 0.0015351824975588203,
                        "99" : 3.7148842741547497e-07,
                        "100" : 0.024319075707463188,
                        "101" : 0.0011950731130103871,
                        "102" : 0.0018790640683053245,
                        "103" : 0.004597378533961716,
                        "104" : 0.001148789381827116,
                        "105" : 0.0005113661362938622,
                        "106" : 0.0261460446913394,
                        "107" : 0.0015818865430710495,
                        "108" : 4.099032586213084e-05,
                        "109" : 1.9692900965931894e-11,
                        "110" : 0.0003357260185165091,
                        "111" : 1.2803189736453037e-06,
                        "112" : 4.5219063718672976e-06,
                        "113" : 1.5072846152012066e-12,
                        "114" : 1.4700309204170904e-13,
                        "115" : 5.8515599656986676e-12,
                        "116" : 0.0003123379914235175,
                        "117" : 0.00021036355395221326,
                        "118" : 0.0006292828539243017,
                        "119" : 0.01915353678477692,
                        "120" : 0.006817203724947416,
                        "121" : 0.019838413010469458,
                        "122" : 0.0827649373977752,
                        "123" : 0.11015594905968608,
                        "124" : 0.0038029468307397138,
                        "125" : 0.015681022504829386,
                        "126" : 0.02866325979405575,
                        "127" : 0.07535279287282422
                    }
                ],
                "frozen" : false
            },
            "name" : "state1",
            "weight" : 1.0
        },
        {
            "class" : "State",
            "distribution" : {
                "class" : "Distribution",
                "dtype" : "int",
                "name" : "DiscreteDistribution",
                "parameters" : [
                    {
                        "0" : 3.106507228418513e-13,
                        "1" : 1.457250481296017e-12,
                        "2" : 6.970988853522555e-12,
                        "3" : 6.672513915789896e-05,
                        "4" : 0.0001430604838533613,
                        "5" : 0.00044977785804472853,
                        "6" : 0.0004216487560443157,
                        "7" : 0.005803522911386133,
                        "8" : 5.976517360343884e-18,
                        "9" : 0.00017591367531592472,
                        "10" : 5.8426352718329356e-05,
                        "11" : 2.461987427427398e-07,
                        "12" : 0.00025361886001310316,
                        "13" : 0.0002515087016135479,
                        "14" : 8.801487620080767e-05,
                        "15" : 0.0021797420695300407,
                        "16" : 3.0926670263872137e-13,
                        "17" : 6.715991603576725e-13,
                        "18" : 9.399894398623299e-14,
                        "19" : 7.816409802856962e-05,
                        "20" : 7.05651508211636e-15,
                        "21" : 1.1652088438786197e-15,
                        "22" : 4.562899064965207e-12,
                        "23" : 3.958467046177706e-05,
                        "24" : 0.0,
                        "25" : 0.0,
                        "26" : 0.0,
                        "27" : 0.00025150870194474805,
                        "28" : 0.0009669171206877704,
                        "29" : 0.0,
                        "30" : 0.0,
                        "31" : 0.0,
                        "32" : 0.0005297084370207529,
                        "33" : 0.00025150835301871203,
                        "34" : 1.1274730887263718e-06,
                        "35" : 0.0,
                        "36" : 0.00033534341280623824,
                        "37" : 0.0,
                        "38" : 0.0,
                        "39" : 0.0,
                        "40" : 8.383623284997228e-05,
                        "41" : 1.4431280225185613e-19,
                        "42" : 0.0002515086448056977,
                        "43" : 2.5783514233849886e-19,
                        "44" : 0.0004984017980161936,
                        "45" : 3.014455645303708e-08,
                        "46" : 2.296268236936674e-12,
                        "47" : 4.2228985413281795e-07,
                        "48" : 0.0005868536190702308,
                        "49" : 7.23005135688565e-05,
                        "50" : 0.0,
                        "51" : 0.0,
                        "52" : 1.4591391447844428e-08,
                        "53" : 0.0012480607826627665,
                        "54" : 0.0,
                        "55" : 0.0,
                        "56" : 2.6056884462129616e-14,
                        "57" : 1.9789381699814137e-17,
                        "58" : 0.0,
                        "59" : 0.0,
                        "60" : 0.0,
                        "61" : 0.0,
                        "62" : 8.387849497207412e-05,
                        "63" : 3.3540032108619644e-05,
                        "64" : 1.656733690295061e-09,
                        "65" : 4.373420074328864e-06,
                        "66" : 1.3611014807916857e-07,
                        "67" : 0.0009524808264116858,
                        "68" : 3.3671198738189167e-10,
                        "69" : 1.0988225317823277e-06,
                        "70" : 1.7604292977475406e-05,
                        "71" : 0.0016887010516505503,
                        "72" : 1.9943303828194566e-10,
                        "73" : 5.880291036333499e-16,
                        "74" : 0.0001639436362651026,
                        "75" : 3.245808107741763e-07,
                        "76" : 1.789485946537141e-09,
                        "77" : 3.7529456385238014e-08,
                        "78" : 5.3142337211736854e-08,
                        "79" : 1.550573030646813e-06,
                        "80" : 0.00010165164878950346,
                        "81" : 3.4606235925118676e-08,
                        "82" : 0.010456603366163634,
                        "83" : 0.007101012598826767,
                        "84" : 0.00037499053190898925,
                        "85" : 0.009695244103725348,
                        "86" : 0.0024920144624361877,
                        "87" : 0.007372185111787993,
                        "88" : 0.0013838253563469845,
                        "89" : 0.03207388840379321,
                        "90" : 0.0005683528504164823,
                        "91" : 0.003036692090809136,
                        "92" : 0.0010256075709762307,
                        "93" : 0.11029781712550545,
                        "94" : 0.006140384276653327,
                        "95" : 0.013605958502997714,
                        "96" : 1.704289496694487e-05,
                        "97" : 0.0027430156879428135,
                        "98" : 0.0005181178395659712,
                        "99" : 0.029306025805800356,
                        "100" : 0.0003085665991436772,
                        "101" : 0.025363753756362854,
                        "102" : 0.029102159047135163,
                        "103" : 0.018004709964155652,
                        "104" : 0.0004006504194737389,
                        "105" : 0.0023012666140009327,
                        "106" : 0.0012369406852544354,
                        "107" : 0.028339379907683867,
                        "108" : 0.016882797643829845,
                        "109" : 0.05770236163160583,
                        "110" : 4.985665081346857e-07,
                        "111" : 0.001237384983320224,
                        "112" : 0.0008652319489838201,
                        "113" : 0.03160410379459438,
                        "114" : 0.01219331093792719,
                        "115" : 0.001341379509465594,
                        "116" : 0.00840352373099884,
                        "117" : 0.06766888971488308,
                        "118" : 0.08555411615083724,
                        "119" : 0.05365707892514248,
                        "120" : 0.11396341754464497,
                        "121" : 0.0728337537759067,
                        "122" : 0.02148899355086914,
                        "123" : 0.00893418105487157,
                        "124" : 0.05010948788545478,
                        "125" : 0.02077733460542275,
                        "126" : 0.012528514469552518,
                        "127" : 0.0008505244680200138
                    }
                ],
                "frozen" : false
            },
            "name" : "state2",
            "weight" : 1.0
        },
        {
            "class" : "State",
            "distribution" : {
                "class" : "Distribution",
                "dtype" : "int",
                "name" : "DiscreteDistribution",
                "parameters" : [
                    {
                        "0" : 0.004006568510496467,
                        "1" : 0.01063801516252001,
                        "2" : 0.0035043055460368773,
                        "3" : 0.052812857076367827,
                        "4" : 9.740100297378658e-05,
                        "5" : 0.0037451082593631395,
                        "6" : 1.2537328757219408e-13,
                        "7" : 1.0868701227351442e-09,
                        "8" : 8.706871711033772e-05,
                        "9" : 7.415760025979606e-12,
                        "10" : 0.0007950887098942647,
                        "11" : 5.76413800233852e-12,
                        "12" : 0.00042249125445546765,
                        "13" : 1.8817908321527337e-16,
                        "14" : 8.074617307885228e-05,
                        "15" : 1.5893637918341434e-11,
                        "16" : 0.0005135518188826778,
                        "17" : 0.0069018868460367,
                        "18" : 0.0799391248703623,
                        "19" : 0.002876118230995501,
                        "20" : 0.00031525085489149363,
                        "21" : 7.903849907939317e-05,
                        "22" : 0.0012678825504608242,
                        "23" : 0.0003175446517302041,
                        "24" : 0.0,
                        "25" : 0.0,
                        "26" : 0.0,
                        "27" : 1.878917649549255e-13,
                        "28" : 0.00028377001307163045,
                        "29" : 0.0,
                        "30" : 0.0,
                        "31" : 0.0,
                        "32" : 4.811632796948212e-10,
                        "33" : 5.736963131403448e-12,
                        "34" : 2.1990444774975907e-15,
                        "35" : 0.0,
                        "36" : 2.782577151680499e-14,
                        "37" : 0.0,
                        "38" : 0.0,
                        "39" : 0.0,
                        "40" : 1.7631398742540687e-18,
                        "41" : 4.8847479498143183e-17,
                        "42" : 4.33850976324003e-12,
                        "43" : 2.1582670484109246e-17,
                        "44" : 8.893422313550698e-05,
                        "45" : 0.00018951171708634905,
                        "46" : 3.800310364211636e-09,
                        "47" : 8.703864828939296e-11,
                        "48" : 2.886738784305658e-15,
                        "49" : 1.174041741288959e-08,
                        "50" : 0.0,
                        "51" : 0.0,
                        "52" : 0.00030903824641905826,
                        "53" : 0.00016740676338402875,
                        "54" : 0.0,
                        "55" : 0.0,
                        "56" : 0.0007296012802518432,
                        "57" : 7.050215251267097e-11,
                        "58" : 0.0,
                        "59" : 0.0,
                        "60" : 0.0,
                        "61" : 0.0,
                        "62" : 8.545807595373386e-05,
                        "63" : 9.547230816115807e-05,
                        "64" : 0.00041186746276639834,
                        "65" : 1.8612186850415336e-08,
                        "66" : 0.018294063687783736,
                        "67" : 0.006845882256314617,
                        "68" : 0.0018985512228377997,
                        "69" : 0.00478459442592918,
                        "70" : 0.02335152885471046,
                        "71" : 0.07374910266109018,
                        "72" : 0.00890927182983909,
                        "73" : 0.008617525498373475,
                        "74" : 0.001284015676045724,
                        "75" : 0.0036414961903343183,
                        "76" : 0.09187679058839643,
                        "77" : 0.10253681857025067,
                        "78" : 0.09441863366015793,
                        "79" : 0.13136325164708187,
                        "80" : 2.1429137369197303e-08,
                        "81" : 2.899147196343323e-13,
                        "82" : 0.0008564978268356425,
                        "83" : 0.00806265938606161,
                        "84" : 0.00011395951741330203,
                        "85" : 0.00015587392234091464,
                        "86" : 0.001566830971720902,
                        "87" : 4.114642755338323e-13,
                        "88" : 0.0100430651651892,
                        "89" : 0.028144842188810665,
                        "90" : 0.14715888122796145,
                        "91" : 0.030872851161985522,
                        "92" : 0.0074882665956829565,
                        "93" : 0.0017973811786228604,
                        "94" : 0.006649704314851173,
                        "95" : 0.00015298544586144633,
                        "96" : 0.005560577741540895,
                        "97" : 0.001679230754355041,
                        "98" : 0.00012669086553624025,
                        "99" : 0.00011443638124780405,
                        "100" : 0.00028307342557377425,
                        "101" : 0.0029936568253755244,
                        "102" : 0.0002755325323730704,
                        "103" : 4.166345461742814e-06,
                        "104" : 0.00016395555827218241,
                        "105" : 3.024071072332732e-06,
                        "106" : 8.242718163475068e-07,
                        "107" : 1.226622728676256e-05,
                        "108" : 0.0031501428120859322,
                        "109" : 8.615306196248869e-05,
                        "110" : 1.9329710841509096e-06,
                        "111" : 7.677541029506738e-06,
                        "112" : 2.532529561298675e-05,
                        "113" : 1.211676118629452e-08,
                        "114" : 6.84522702176909e-13,
                        "115" : 1.426262778981354e-10,
                        "116" : 2.384894373001698e-05,
                        "117" : 1.464424907669806e-11,
                        "118" : 1.1683160242567293e-08,
                        "119" : 5.700563414004756e-13,
                        "120" : 2.091478075836348e-09,
                        "121" : 1.0676427941186457e-10,
                        "122" : 9.077810632831648e-05,
                        "123" : 3.914332985884424e-15,
                        "124" : 1.8756645148530781e-07,
                        "125" : 6.990855185429377e-10,
                        "126" : 7.520582496911533e-13,
                        "127" : 2.0879031124403863e-15
                    }
                ],
                "frozen" : false
            },
            "name" : "state3",
            "weight" : 1.0
        },
        {
            "class" : "State",
            "distribution" : null,
            "name" : "C-start",
            "weight" : 1.0
        },
        {
            "class" : "State",
            "distribution" : null,
            "name" : "C-end",
            "weight" : 1.0
        }
    ],
    "end_index" : 5,
    "start_index" : 4,
    "silent_index" : 4,
    "edges" : [
        [
            4,
            0,
            0.09121629045896217,
            0.25,
            null
        ],
        [
            4,
            1,
            0.43805551096516865,
            0.25,
            null
        ],
        [
            4,
            2,
            0.46731517652389987,
            0.25,
            null
        ],
        [
            4,
            3,
            0.003413022051969406,
            0.25,
            null
        ],
        [
            0,
            0,
            0.9548173379641842,
            0.25,
            null
        ],
        [
            0,
            1,
            0.011185277272334027,
            0.25,
            null
        ],
        [
            0,
            2,
            0.012996441310764429,
            0.25,
            null
        ],
        [
            0,
            3,
            0.021000943452717274,
            0.25,
            null
        ],
        [
            1,
            0,
            0.015033517147103234,
            0.25,
            null
        ],
        [
            1,
            1,
            0.9552589876010692,
            0.25,
            null
        ],
        [
            1,
            2,
            0.014442382176383987,
            0.25,
            null
        ],
        [
            1,
            3,
            0.01526511307544364,
            0.25,
            null
        ],
        [
            2,
            0,
            0.025336358302423565,
            0.25,
            null
        ],
        [
            2,
            1,
            0.015533204268327864,
            0.25,
            null
        ],
        [
            2,
            2,
            0.9535433731544127,
            0.25,
            null
        ],
        [
            2,
            3,
            0.005587064274835868,
            0.25,
            null
        ],
        [
            3,
            0,
            0.032135439572952514,
            0.25,
            null
        ],
        [
            3,
            1,
            0.017559854938230236,
            0.25,
            null
        ],
        [
            3,
            2,
            0.0065680802750413885,
            0.25,
            null
        ],
        [
            3,
            3,
            0.9437366252137758,
            0.25,
            null
        ]
    ],
    "distribution ties" : []
}